botibot/__init__.py
botibot/_version.py
botibot/cli.py
botibot/gsm/__init__.py
botibot/gsm/cli.py
botibot/gsm/sim800L.py
botibot/infrared/__init__.py
botibot/infrared/infrared_sensor.py
botibot/ir_temp/__init__.py
botibot/ir_temp/gy906.py
botibot/motor/__init__.py
botibot/motor/motor_controller.py
botibot/oled/__init__.py
botibot/oled/oled_display.py
botibot/relay/__init__.py
botibot/relay/relay_controller.py
botibot/scheduler/__init__.py
botibot/scheduler/cli.py
botibot/servo/__init__.py
botibot/servo/servo_controller.py
botibot/ultrasonic/__init__.py
botibot/ultrasonic/ultrasonic_sensor.py
botibot/webserver/README.md
botibot/webserver/__init__.py
botibot/webserver/flask_server.py
botibot/webserver/pill_dispenser_dashboard.py
botibot/webserver/run_dashboard.py
botibot_py-1.0.6.dist-info/licenses/LICENSE
botibot_py-1.0.6.dist-info/METADATA
botibot_py-1.0.6.dist-info/WHEEL
botibot_py-1.0.6.dist-info/entry_points.txt
botibot_py-1.0.6.dist-info/top_level.txt
botibot_py-1.0.6.dist-info/RECORD
