Metadata-Version: 2.4
Name: botibot.py
Version: 1.0.6
Summary: A python package for Project Botibot with gpiozero integration
Home-page: https://github.com/deJames-13/botibot.py
Author: deJames-13
Author-email: deJames-13 <de.james013@gmail.com>
Maintainer-email: deJames-13 <de.james013@gmail.com>
License-Expression: MIT
Project-URL: Homepage, https://github.com/deJames-13/botibot.py
Project-URL: Documentation, https://github.com/deJames-13/botibot.py/blob/main/README.md
Project-URL: Repository, https://github.com/deJames-13/botibot.py.git
Project-URL: Bug Tracker, https://github.com/deJames-13/botibot.py/issues
Project-URL: Changelog, https://github.com/deJames-13/botibot.py/blob/main/CHANGELOG.md
Keywords: modules.py,modules,raspberry-pi,microcontroller,servo,oled,relay,infrared,ultrasonic,motor,gpio,gpiozero,iot,embedded,hardware,automation,robotics,project
Platform: Linux
Classifier: Development Status :: 4 - Beta
Classifier: Intended Audience :: Education
Classifier: Intended Audience :: Developers
Classifier: Topic :: Education
Classifier: Topic :: System :: Hardware
Classifier: Topic :: System :: Hardware :: Hardware Drivers
Classifier: Programming Language :: Python :: 3
Classifier: Programming Language :: Python :: 3.7
Classifier: Programming Language :: Python :: 3.8
Classifier: Programming Language :: Python :: 3.9
Classifier: Programming Language :: Python :: 3.10
Classifier: Programming Language :: Python :: 3.11
Classifier: Operating System :: POSIX :: Linux
Classifier: Environment :: Other Environment
Requires-Python: >=3.7
License-File: LICENSE
Requires-Dist: adafruit-circuitpython-ssd1306
Requires-Dist: adafruit-blinka
Requires-Dist: Pillow
Requires-Dist: RPi.GPIO
Requires-Dist: gpiozero
Requires-Dist: Flask
Requires-Dist: Flask-CORS
Requires-Dist: python-dateutil
Requires-Dist: adafruit-circuitpython-mlx90614
Requires-Dist: pyserial
Requires-Dist: schedule
Requires-Dist: apscheduler
Provides-Extra: dev
Requires-Dist: pytest>=6.0; extra == "dev"
Requires-Dist: pytest-cov; extra == "dev"
Requires-Dist: black; extra == "dev"
Requires-Dist: flake8; extra == "dev"
Requires-Dist: mypy; extra == "dev"
Requires-Dist: pre-commit; extra == "dev"
Provides-Extra: docs
Requires-Dist: sphinx; extra == "docs"
Requires-Dist: sphinx-rtd-theme; extra == "docs"
Requires-Dist: myst-parser; extra == "docs"
Provides-Extra: full
Requires-Dist: matplotlib; extra == "full"
Requires-Dist: numpy; extra == "full"
Requires-Dist: scipy; extra == "full"
Dynamic: author
Dynamic: home-page
Dynamic: license-file
Dynamic: platform
Dynamic: requires-python
